{
  "aweme_list": [
    {
      "added_sound_music_info": {
        "album": "",
        "artists": [],
        "audition_duration": 18,
        "author": "montana",
        "author_deleted": false,
        "author_position": null,
        "avatar_medium": {
          "height": 720,
          "uri": "tos-maliva-avt-0068/b78964318baeb4ea6db2a13738a379c5",
          "url_list": [
            "https://p16-sign-va.tiktokcdn.com/tos-maliva-avt-0068/b78964318baeb4ea6db2a13738a379c5~c5_720x720.webp?x-expires=1682182800&x-signature=43gyMj6XbxySybYXShIrEVCgBLE%3D",
            "https://p16-sign-va.tiktokcdn.com/tos-maliva-avt-0068/b78964318baeb4ea6db2a13738a379c5~c5_720x720.jpeg?x-expires=1682182800&x-signature=Win6sRC52Fun2%2BVX3f5UAk0EA1A%3D"
          ],
          "width": 720
        },
        "avatar_thumb": {
          "height": 720,
          "uri": "tos-maliva-avt-0068/b78964318baeb4ea6db2a13738a379c5",
          "url_list": [
            "https://p16-sign-va.tiktokcdn.com/tos-maliva-avt-0068/b78964318baeb4ea6db2a13738a379c5~c5_100x100.webp?x-expires=1682182800&x-signature=pJjDghXFEEAyHfiOlOARCG3FlHk%3D",
            "https://p16-sign-va.tiktokcdn.com/tos-maliva-avt-0068/b78964318baeb4ea6db2a13738a379c5~c5_100x100.jpeg?x-expires=1682182800&x-signature=kYwxyunabOHwDNkNy%2BMRjhpUGjo%3D"
          ],
          "width": 720
        },
        "binded_challenge_id": 0,
        "can_not_reuse": false,
        "collect_stat": 0,
        "commercial_right_type": 2,
        "cover_large": {
          "height": 720,
          "uri": "tos-maliva-avt-0068/b78964318baeb4ea6db2a13738a379c5",
          "url_list": [
            "https://p16-sign-va.tiktokcdn.com/tos-maliva-avt-0068/b78964318baeb4ea6db2a13738a379c5~c5_1080x1080.webp?x-expires=1682182800&x-signature=xrB1NOSUNcPeGnGAgSc0YTFlz84%3D",
            "https://p16-sign-va.tiktokcdn.com/tos-maliva-avt-0068/b78964318baeb4ea6db2a13738a379c5~c5_1080x1080.jpeg?x-expires=1682182800&x-signature=P9eTFGd28ZeMdeUMm3O2J14qJNM%3D"
          ],
          "width": 720
        },
        "cover_medium": {
          "height": 720,
          "uri": "tos-maliva-avt-0068/b78964318baeb4ea6db2a13738a379c5",
          "url_list": [
            "https://p16-sign-va.tiktokcdn.com/tos-maliva-avt-0068/b78964318baeb4ea6db2a13738a379c5~c5_720x720.webp?x-expires=1682182800&x-signature=43gyMj6XbxySybYXShIrEVCgBLE%3D",
            "https://p16-sign-va.tiktokcdn.com/tos-maliva-avt-0068/b78964318baeb4ea6db2a13738a379c5~c5_720x720.jpeg?x-expires=1682182800&x-signature=Win6sRC52Fun2%2BVX3f5UAk0EA1A%3D"
          ],
          "width": 720
        },
        "cover_thumb": {
          "height": 720,
          "uri": "tos-maliva-avt-0068/b78964318baeb4ea6db2a13738a379c5",
          "url_list": [
            "https://p16-sign-va.tiktokcdn.com/tos-maliva-avt-0068/b78964318baeb4ea6db2a13738a379c5~c5_100x100.webp?x-expires=1682182800&x-signature=pJjDghXFEEAyHfiOlOARCG3FlHk%3D",
            "https://p16-sign-va.tiktokcdn.com/tos-maliva-avt-0068/b78964318baeb4ea6db2a13738a379c5~c5_100x100.jpeg?x-expires=1682182800&x-signature=kYwxyunabOHwDNkNy%2BMRjhpUGjo%3D"
          ],
          "width": 720
        },
        "dmv_auto_show": false,
        "duration": 18,
        "duration_high_precision": {
          "audition_duration_precision": 18.860374,
          "duration_precision": 18.860374,
          "shoot_duration_precision": 18.860374,
          "video_duration_precision": 18.860374
        },
        "external_song_info": [],
        "extra": "{\"aed_music_dur\":18.885,\"beats\":{},\"can_read\":true,\"can_reuse\":true,\"erase_type\":0,\"erase_uid\":0,\"from_user_id\":0,\"has_edited\":0,\"is_ugc_mapping\":true,\"is_used\":1,\"owner_id\":6795665266924995590,\"resource_status\":0,\"review_unshelve_reason\":0,\"reviewed\":0,\"schedule_search_time\":0}",
        "id": 7216022098816568069,
        "id_str": "7216022098816568069",
        "is_audio_url_with_cookie": false,
        "is_author_artist": false,
        "is_commerce_music": true,
        "is_matched_metadata": false,
        "is_original": false,
        "is_original_sound": true,
        "is_pgc": false,
        "is_play_music": false,
        "is_shooting_allow": true,
        "lyric_short_position": null,
        "matched_pgc_sound": {
          "author": "Montana.mp3",
          "mixed_author": "Contains music from: \"KLAJ KLAJ\"",
          "mixed_title": "original sound - montana.mp7 (Contains music from: KLAJ KLAJ - Montana.mp3)",
          "music_release_info": {
            "group_release_date": 0,
            "is_new_release_song": false
          },
          "title": "KLAJ KLAJ"
        },
        "matched_song": {
          "author": "Montana.mp3",
          "chorus_info": {
            "duration_ms": 30528,
            "start_ms": 9792
          },
          "cover_medium": {
            "height": 720,
            "uri": "tos-alisg-v-2774/cb23c9b03e07452d9db378e549b3ff6d",
            "url_list": [
              "https://p16-sg.tiktokcdn.com/aweme/200x200/tos-alisg-v-2774/cb23c9b03e07452d9db378e549b3ff6d.jpeg"
            ],
            "width": 720
          },
          "h5_url": "",
          "id": "7223001877313488898",
          "performers": null,
          "title": "KLAJ KLAJ"
        },
        "mid": "7216022098816568069",
        "multi_bit_rate_play_info": null,
        "mute_share": false,
        "offline_desc": "",
        "owner_handle": "montana.mp7",
        "owner_id": "6795665266924995590",
        "owner_nickname": "montana",
        "play_url": {
          "height": 720,
          "uri": "https://sf77-ies-music-va.tiktokcdn.com/obj/musically-maliva-obj/7216022103279389446.mp3",
          "url_list": [
            "https://sf77-ies-music-va.tiktokcdn.com/obj/musically-maliva-obj/7216022103279389446.mp3"
          ],
          "width": 720
        },
        "position": null,
        "prevent_download": false,
        "preview_end_time": 0,
        "preview_start_time": 0,
        "search_highlight": null,
        "sec_uid": "MS4wLjABAAAAYILLPeI9L6rdAQKF1rBEPbAzkE5gjdU0N5Y-7bWGxsrSVbdHwoqQboPdGvwJr6q7",
        "shoot_duration": 18,
        "source_platform": 72,
        "status": 1,
        "tag_list": null,
        "title": "original sound - montana.mp7",
        "tt_to_dsp_song_infos": null,
        "user_count": 0,
        "video_duration": 18
      },
      "anchors": null,
      "anchors_extras": "",
      "author": {
        "accept_private_policy": false,
        "account_labels": null,
        "account_region": "",
        "ad_cover_url": null,
        "advance_feature_item_order": null,
        "advanced_feature_info": null,
        "apple_account": 0,
        "authority_status": 0,
        "avatar_168x168": {
          "height": 720,
          "uri": "tos-maliva-avt-0068/6e13913c35be4cd0c86377207eded1ea",
          "url_list": [
            "https://p16-sign-va.tiktokcdn.com/tos-maliva-avt-0068/6e13913c35be4cd0c86377207eded1ea~c5_168x168.webp?x-expires=1682182800&x-signature=7ggXFoS7kAxwIc0yZJz7P7CIVXo%3D",
            "https://p16-sign-va.tiktokcdn.com/tos-maliva-avt-0068/6e13913c35be4cd0c86377207eded1ea~c5_168x168.jpeg?x-expires=1682182800&x-signature=YuQAYvho1jVbJXoKI%2BEoPBrcwt4%3D"
          ],
          "width": 720
        },
        "avatar_300x300": {
          "height": 720,
          "uri": "tos-maliva-avt-0068/6e13913c35be4cd0c86377207eded1ea",
          "url_list": [
            "https://p16-sign-va.tiktokcdn.com/tos-maliva-avt-0068/6e13913c35be4cd0c86377207eded1ea~c5_300x300.webp?x-expires=1682182800&x-signature=DGL8k%2BedQWXDoNUrQUYf%2FrTFTFs%3D",
            "https://p16-sign-va.tiktokcdn.com/tos-maliva-avt-0068/6e13913c35be4cd0c86377207eded1ea~c5_300x300.jpeg?x-expires=1682182800&x-signature=kk5bBViIDBq1cpedt4FGPye1LSQ%3D"
          ],
          "width": 720
        },
        "avatar_larger": {
          "height": 720,
          "uri": "tos-maliva-avt-0068/6e13913c35be4cd0c86377207eded1ea",
          "url_list": [
            "https://p16-sign-va.tiktokcdn.com/tos-maliva-avt-0068/6e13913c35be4cd0c86377207eded1ea~c5_1080x1080.webp?x-expires=1682182800&x-signature=au%2FhTqptaUKRGZzq57XfuDpWWVc%3D",
            "https://p16-sign-va.tiktokcdn.com/tos-maliva-avt-0068/6e13913c35be4cd0c86377207eded1ea~c5_1080x1080.jpeg?x-expires=1682182800&x-signature=1g1tOrXSM21oFNyOfBk0Uaxf8gM%3D"
          ],
          "width": 720
        },
        "avatar_medium": {
          "height": 720,
          "uri": "tos-maliva-avt-0068/6e13913c35be4cd0c86377207eded1ea",
          "url_list": [
            "https://p16-sign-va.tiktokcdn.com/tos-maliva-avt-0068/6e13913c35be4cd0c86377207eded1ea~c5_720x720.webp?x-expires=1682182800&x-signature=nIQkaEiPTfnU9xw0Qb8euOgDU%2Fg%3D",
            "https://p16-sign-va.tiktokcdn.com/tos-maliva-avt-0068/6e13913c35be4cd0c86377207eded1ea~c5_720x720.jpeg?x-expires=1682182800&x-signature=UkRkxDHMDx98N8R8cA%2FFwei4%2FM0%3D"
          ],
          "width": 720
        },
        "avatar_thumb": {
          "height": 720,
          "uri": "tos-maliva-avt-0068/6e13913c35be4cd0c86377207eded1ea",
          "url_list": [
            "https://p16-sign-va.tiktokcdn.com/tos-maliva-avt-0068/6e13913c35be4cd0c86377207eded1ea~c5_100x100.webp?x-expires=1682182800&x-signature=7L2vuwclnrpV0oqENBVxLoCBD0I%3D",
            "https://p16-sign-va.tiktokcdn.com/tos-maliva-avt-0068/6e13913c35be4cd0c86377207eded1ea~c5_100x100.jpeg?x-expires=1682182800&x-signature=4z8d1tWG4qWtaRTO%2B429%2BD29Sqc%3D"
          ],
          "width": 720
        },
        "avatar_uri": "tos-maliva-avt-0068/6e13913c35be4cd0c86377207eded1ea",
        "aweme_count": 1,
        "bind_phone": "",
        "bold_fields": null,
        "can_message_follow_status_list": null,
        "can_set_geofencing": null,
        "cha_list": null,
        "comment_filter_status": 0,
        "comment_setting": 0,
        "commerce_user_level": 0,
        "cover_url": [
          {
            "height": 720,
            "uri": "tiktok-obj/1613727517271041",
            "url_list": [
              "https://p16-sg.tiktokcdn.com/obj/tiktok-obj/1613727517271041"
            ],
            "width": 720
          }
        ],
        "create_time": 0,
        "custom_verify": "",
        "cv_level": "",
        "download_prompt_ts": 1682086242,
        "download_setting": 0,
        "duet_setting": 0,
        "enterprise_verify_reason": "",
        "events": null,
        "favoriting_count": 7,
        "fb_expire_time": 0,
        "follow_status": 0,
        "follower_count": 0,
        "follower_status": 0,
        "followers_detail": null,
        "following_count": 1,
        "friends_status": 0,
        "geofencing": null,
        "google_account": "",
        "has_email": false,
        "has_facebook_token": false,
        "has_insights": false,
        "has_orders": false,
        "has_twitter_token": false,
        "has_youtube_token": false,
        "hide_search": false,
        "homepage_bottom_toast": null,
        "ins_id": "",
        "is_ad_fake": false,
        "is_block": false,
        "is_discipline_member": false,
        "is_phone_binded": false,
        "is_star": false,
        "item_list": null,
        "language": "en",
        "live_agreement": 0,
        "live_commerce": false,
        "live_verify": 0,
        "mention_status": 1,
        "mutual_relation_avatars": null,
        "need_points": null,
        "need_recommend": 0,
        "nickname": "nuccii",
        "original_musician": {
          "digg_count": 0,
          "music_count": 0,
          "music_used_count": 0,
          "new_release_clip_ids": null
        },
        "platform_sync_info": null,
        "prevent_download": false,
        "react_setting": 0,
        "region": "RS",
        "relative_users": null,
        "room_id": 0,
        "search_highlight": null,
        "sec_uid": "MS4wLjABAAAAWFspuXtIqdYnKm0zJfns_yIeC9t_lowZZPMUJ5cL8MvoPZZTeU8clvfh-a8B80pN",
        "secret": 0,
        "share_info": {
          "now_invitation_card_image_urls": null,
          "share_desc": "",
          "share_desc_info": "",
          "share_qrcode_url": {
            "height": 720,
            "uri": "",
            "url_list": [],
            "width": 720
          },
          "share_title": "",
          "share_title_myself": "",
          "share_title_other": "",
          "share_url": ""
        },
        "share_qrcode_uri": "",
        "shield_comment_notice": 0,
        "shield_digg_notice": 0,
        "shield_edit_field_info": null,
        "shield_follow_notice": 0,
        "short_id": "0",
        "show_image_bubble": false,
        "signature": "follow meni follw tebi",
        "special_account": {
          "special_account_list": null
        },
        "special_lock": 1,
        "status": 1,
        "stitch_setting": 0,
        "total_favorited": 0,
        "tw_expire_time": 0,
        "twitter_id": "",
        "twitter_name": "",
        "type_label": null,
        "uid": "7222929347358327813",
        "unique_id": "nuccii22",
        "unique_id_modify_time": 1681719444,
        "user_canceled": false,
        "user_mode": 1,
        "user_period": 0,
        "user_profile_guide": null,
        "user_rate": 1,
        "user_tags": null,
        "verification_type": 1,
        "verify_info": "",
        "video_icon": {
          "height": 720,
          "uri": "",
          "url_list": [],
          "width": 720
        },
        "white_cover_url": null,
        "with_commerce_entry": false,
        "with_shop_entry": false,
        "youtube_channel_id": "",
        "youtube_channel_title": "",
        "youtube_expire_time": 0
      },
      "author_user_id": 7222929347358327813,
      "aweme_acl": {
        "download_general": {
          "code": 0,
          "extra": "#",
          "mute": false,
          "show_type": 2,
          "transcode": 2
        },
        "download_mask_panel": {
          "code": 0,
          "extra": "#",
          "mute": false,
          "show_type": 2,
          "transcode": 2
        },
        "platform_list": null,
        "share_general": {
          "code": 0,
          "extra": "#",
          "mute": false,
          "show_type": 2,
          "transcode": 2
        },
        "share_list_status": 0
      },
      "aweme_id": "7224505414501960966",
      "aweme_type": 0,
      "behind_the_song_music_ids": null,
      "behind_the_song_video_music_ids": null,
      "bodydance_score": 0,
      "branded_content_accounts": null,
      "cc_template_info": {
        "author_name": "",
        "clip_count": 0,
        "desc": "",
        "duration_milliseconds": 0,
        "related_music_id": "",
        "template_id": ""
      },
      "cha_list": null,
      "challenge_position": null,
      "cmt_swt": false,
      "collect_stat": 0,
      "commerce_config_data": null,
      "commerce_info": {
        "adv_promotable": false,
        "auction_ad_invited": false,
        "with_comment_filter_words": false
      },
      "content_desc": "",
      "content_desc_extra": [],
      "cover_labels": null,
      "create_time": 1682086248,
      "desc": "",
      "desc_language": "un",
      "disable_search_trending_bar": false,
      "distance": "",
      "distribute_type": 1,
      "follow_up_item_id_groups": "",
      "follow_up_publish_from_id": -1,
      "geofencing": null,
      "geofencing_regions": null,
      "green_screen_materials": null,
      "group_id": "7223088351073602822",
      "group_id_list": {
        "GroupdIdList0": null,
        "GroupdIdList1": null
      },
      "has_vs_entry": false,
      "have_dashboard": false,
      "hybrid_label": null,
      "image_infos": null,
      "interact_permission": {
        "allow_adding_to_story": 1,
        "allow_create_sticker": {
          "status": 2
        },
        "duet": 0,
        "duet_privacy_setting": 0,
        "stitch": 0,
        "stitch_privacy_setting": 0,
        "upvote": 0
      },
      "interaction_stickers": null,
      "is_ads": false,
      "is_description_translatable": false,
      "is_hash_tag": 1,
      "is_on_this_day": 0,
      "is_pgcshow": false,
      "is_preview": 0,
      "is_relieve": false,
      "is_text_sticker_translatable": false,
      "is_top": 0,
      "is_vr": false,
      "item_comment_settings": 0,
      "item_duet": 0,
      "item_react": 0,
      "item_stitch": 0,
      "label_top": {
        "height": 720,
        "uri": "tiktok-obj/1598708589477025.PNG",
        "url_list": [
          "https://p16-sg.tiktokcdn.com/obj/tiktok-obj/1598708589477025.PNG"
        ],
        "width": 720
      },
      "label_top_text": null,
      "long_video": null,
      "mask_infos": [],
      "misc_info": "{}",
      "muf_comment_info_v2": null,
      "music": {
        "album": "",
        "artists": [],
        "audition_duration": 18,
        "author": "montana",
        "author_deleted": false,
        "author_position": null,
        "avatar_medium": {
          "height": 720,
          "uri": "tos-maliva-avt-0068/b78964318baeb4ea6db2a13738a379c5",
          "url_list": [
            "https://p16-sign-va.tiktokcdn.com/tos-maliva-avt-0068/b78964318baeb4ea6db2a13738a379c5~c5_720x720.webp?x-expires=1682182800&x-signature=43gyMj6XbxySybYXShIrEVCgBLE%3D",
            "https://p16-sign-va.tiktokcdn.com/tos-maliva-avt-0068/b78964318baeb4ea6db2a13738a379c5~c5_720x720.jpeg?x-expires=1682182800&x-signature=Win6sRC52Fun2%2BVX3f5UAk0EA1A%3D"
          ],
          "width": 720
        },
        "avatar_thumb": {
          "height": 720,
          "uri": "tos-maliva-avt-0068/b78964318baeb4ea6db2a13738a379c5",
          "url_list": [
            "https://p16-sign-va.tiktokcdn.com/tos-maliva-avt-0068/b78964318baeb4ea6db2a13738a379c5~c5_100x100.webp?x-expires=1682182800&x-signature=pJjDghXFEEAyHfiOlOARCG3FlHk%3D",
            "https://p16-sign-va.tiktokcdn.com/tos-maliva-avt-0068/b78964318baeb4ea6db2a13738a379c5~c5_100x100.jpeg?x-expires=1682182800&x-signature=kYwxyunabOHwDNkNy%2BMRjhpUGjo%3D"
          ],
          "width": 720
        },
        "binded_challenge_id": 0,
        "can_not_reuse": false,
        "collect_stat": 0,
        "commercial_right_type": 2,
        "cover_large": {
          "height": 720,
          "uri": "tos-maliva-avt-0068/b78964318baeb4ea6db2a13738a379c5",
          "url_list": [
            "https://p16-sign-va.tiktokcdn.com/tos-maliva-avt-0068/b78964318baeb4ea6db2a13738a379c5~c5_1080x1080.webp?x-expires=1682182800&x-signature=xrB1NOSUNcPeGnGAgSc0YTFlz84%3D",
            "https://p16-sign-va.tiktokcdn.com/tos-maliva-avt-0068/b78964318baeb4ea6db2a13738a379c5~c5_1080x1080.jpeg?x-expires=1682182800&x-signature=P9eTFGd28ZeMdeUMm3O2J14qJNM%3D"
          ],
          "width": 720
        },
        "cover_medium": {
          "height": 720,
          "uri": "tos-maliva-avt-0068/b78964318baeb4ea6db2a13738a379c5",
          "url_list": [
            "https://p16-sign-va.tiktokcdn.com/tos-maliva-avt-0068/b78964318baeb4ea6db2a13738a379c5~c5_720x720.webp?x-expires=1682182800&x-signature=43gyMj6XbxySybYXShIrEVCgBLE%3D",
            "https://p16-sign-va.tiktokcdn.com/tos-maliva-avt-0068/b78964318baeb4ea6db2a13738a379c5~c5_720x720.jpeg?x-expires=1682182800&x-signature=Win6sRC52Fun2%2BVX3f5UAk0EA1A%3D"
          ],
          "width": 720
        },
        "cover_thumb": {
          "height": 720,
          "uri": "tos-maliva-avt-0068/b78964318baeb4ea6db2a13738a379c5",
          "url_list": [
            "https://p16-sign-va.tiktokcdn.com/tos-maliva-avt-0068/b78964318baeb4ea6db2a13738a379c5~c5_100x100.webp?x-expires=1682182800&x-signature=pJjDghXFEEAyHfiOlOARCG3FlHk%3D",
            "https://p16-sign-va.tiktokcdn.com/tos-maliva-avt-0068/b78964318baeb4ea6db2a13738a379c5~c5_100x100.jpeg?x-expires=1682182800&x-signature=kYwxyunabOHwDNkNy%2BMRjhpUGjo%3D"
          ],
          "width": 720
        },
        "dmv_auto_show": false,
        "duration": 18,
        "duration_high_precision": {
          "audition_duration_precision": 18.860374,
          "duration_precision": 18.860374,
          "shoot_duration_precision": 18.860374,
          "video_duration_precision": 18.860374
        },
        "external_song_info": [],
        "extra": "{\"aed_music_dur\":18.885,\"beats\":{},\"can_read\":true,\"can_reuse\":true,\"erase_type\":0,\"erase_uid\":0,\"from_user_id\":0,\"has_edited\":0,\"is_ugc_mapping\":true,\"is_used\":1,\"owner_id\":6795665266924995590,\"resource_status\":0,\"review_unshelve_reason\":0,\"reviewed\":0,\"schedule_search_time\":0}",
        "id": 7216022098816568069,
        "id_str": "7216022098816568069",
        "is_audio_url_with_cookie": false,
        "is_author_artist": false,
        "is_commerce_music": true,
        "is_matched_metadata": false,
        "is_original": false,
        "is_original_sound": true,
        "is_pgc": false,
        "is_play_music": false,
        "is_shooting_allow": true,
        "lyric_short_position": null,
        "matched_pgc_sound": {
          "author": "Montana.mp3",
          "mixed_author": "Contains music from: \"KLAJ KLAJ\"",
          "mixed_title": "original sound - montana.mp7 (Contains music from: KLAJ KLAJ - Montana.mp3)",
          "music_release_info": {
            "group_release_date": 0,
            "is_new_release_song": false
          },
          "title": "KLAJ KLAJ"
        },
        "matched_song": {
          "author": "Montana.mp3",
          "chorus_info": {
            "duration_ms": 30528,
            "start_ms": 9792
          },
          "cover_medium": {
            "height": 720,
            "uri": "tos-alisg-v-2774/cb23c9b03e07452d9db378e549b3ff6d",
            "url_list": [
              "https://p16-sg.tiktokcdn.com/aweme/200x200/tos-alisg-v-2774/cb23c9b03e07452d9db378e549b3ff6d.jpeg"
            ],
            "width": 720
          },
          "h5_url": "",
          "id": "7223001877313488898",
          "performers": null,
          "title": "KLAJ KLAJ"
        },
        "mid": "7216022098816568069",
        "multi_bit_rate_play_info": null,
        "mute_share": false,
        "offline_desc": "",
        "owner_handle": "montana.mp7",
        "owner_id": "6795665266924995590",
        "owner_nickname": "montana",
        "play_url": {
          "height": 720,
          "uri": "https://sf77-ies-music-va.tiktokcdn.com/obj/musically-maliva-obj/7216022103279389446.mp3",
          "url_list": [
            "https://sf77-ies-music-va.tiktokcdn.com/obj/musically-maliva-obj/7216022103279389446.mp3"
          ],
          "width": 720
        },
        "position": null,
        "prevent_download": false,
        "preview_end_time": 0,
        "preview_start_time": 0,
        "search_highlight": null,
        "sec_uid": "MS4wLjABAAAAYILLPeI9L6rdAQKF1rBEPbAzkE5gjdU0N5Y-7bWGxsrSVbdHwoqQboPdGvwJr6q7",
        "shoot_duration": 18,
        "source_platform": 72,
        "status": 1,
        "tag_list": null,
        "title": "original sound - montana.mp7",
        "tt_to_dsp_song_infos": null,
        "user_count": 0,
        "video_duration": 18
      },
      "music_begin_time_in_ms": 0,
      "music_end_time_in_ms": 19800,
      "music_selected_from": "single_song",
      "music_title_style": 0,
      "music_volume": "1.000000",
      "need_trim_step": false,
      "need_vs_entry": false,
      "nickname_position": null,
      "no_selected_music": false,
      "origin_comment_ids": null,
      "origin_volume": "100.000000",
      "original_client_text": {
        "markup_text": "",
        "text_extra": null
      },
      "playlist_blocked": false,
      "poi_re_tag_signal": 0,
      "position": null,
      "prevent_download": false,
      "products_info": null,
      "question_list": null,
      "rate": 12,
      "reference_tts_voice_ids": null,
      "reference_voice_filter_ids": null,
      "region": "RS",
      "retry_type": 1,
      "risk_infos": {
        "content": "",
        "risk_sink": false,
        "type": 0,
        "vote": false,
        "warn": false
      },
      "search_highlight": null,
      "share_info": {
        "bool_persist": 0,
        "now_invitation_card_image_urls": null,
        "share_desc": "Check out nuccii's video! #TikTok",
        "share_desc_info": "TikTok: Make Every Second CountCheck out nuccii\u2019s video! #TikTok > ",
        "share_link_desc": "",
        "share_quote": "",
        "share_signature_desc": "",
        "share_signature_url": "",
        "share_title": "Check out nuccii\u2019s video! #TikTok > ",
        "share_title_myself": "",
        "share_title_other": "",
        "share_url": "https://www.tiktok.com/@nuccii22/video/7224505414501960966?_r=1&u_code=0&preview_pb=0&sharer_language=en&_d=e7ecdl2k79m3c2&share_item_id=7224505414501960966&source=h5_m",
        "whatsapp_desc": "Download TikTok and watch more fun videos:"
      },
      "share_url": "https://www.tiktok.com/@nuccii22/video/7224505414501960966?_r=1&u_code=0&preview_pb=0&sharer_language=en&_d=e7ecdl2k79m3c2&share_item_id=7224505414501960966&source=h5_m",
      "sort_label": "",
      "statistics": {
        "aweme_id": "7224505414501960966",
        "collect_count": 0,
        "comment_count": 0,
        "digg_count": 0,
        "download_count": 0,
        "forward_count": 0,
        "lose_comment_count": 0,
        "lose_count": 0,
        "play_count": 0,
        "share_count": 0,
        "whatsapp_share_count": 0
      },
      "status": {
        "allow_comment": true,
        "allow_share": true,
        "aweme_id": "7224505414501960966",
        "download_status": 0,
        "in_reviewing": false,
        "is_delete": false,
        "is_prohibited": false,
        "private_status": 0,
        "review_result": {
          "review_status": 0
        },
        "reviewed": 0,
        "self_see": false
      },
      "text_extra": [],
      "text_sticker_major_lang": "un",
      "tts_voice_ids": null,
      "uniqid_position": null,
      "user_digged": 0,
      "video": {
        "CoverTsp": 0,
        "ai_dynamic_cover": {
          "uri": "tos-maliva-p-0068/c91815e2681645ecb129a2fc778634b9_1682086250",
          "url_list": [
            "https://p16-sign-va.tiktokcdn.com/obj/tos-maliva-p-0068/c91815e2681645ecb129a2fc778634b9_1682086250?x-expires=1682182800&x-signature=7vTZ4pOxaebqU9cq%2Biqll%2BexQXU%3D&s=PUBLISH&se=false&sh=&sc=dynamic_cover&l=202304211718510101040280782CB0FEFA"
          ]
        },
        "ai_dynamic_cover_bak": {
          "uri": "tos-maliva-p-0068/c91815e2681645ecb129a2fc778634b9_1682086250",
          "url_list": [
            "https://p16-sign-va.tiktokcdn.com/obj/tos-maliva-p-0068/c91815e2681645ecb129a2fc778634b9_1682086250?x-expires=1682182800&x-signature=7vTZ4pOxaebqU9cq%2Biqll%2BexQXU%3D&s=PUBLISH&se=false&sh=&sc=dynamic_cover&l=202304211718510101040280782CB0FEFA"
          ]
        },
        "animated_cover": {
          "uri": "tos-maliva-p-0068/c91815e2681645ecb129a2fc778634b9_1682086250",
          "url_list": [
            "https://p16-sign-va.tiktokcdn.com/obj/tos-maliva-p-0068/c91815e2681645ecb129a2fc778634b9_1682086250?x-expires=1682182800&x-signature=7vTZ4pOxaebqU9cq%2Biqll%2BexQXU%3D&s=PUBLISH&se=false&sh=&sc=dynamic_cover&l=202304211718510101040280782CB0FEFA"
          ]
        },
        "big_thumbs": [],
        "bit_rate": [
          {
            "HDR_bit": "",
            "HDR_type": "",
            "bit_rate": 1584593,
            "dub_infos": null,
            "gear_name": "normal_540_0",
            "is_bytevc1": 0,
            "play_addr": {
              "data_size": 3923255,
              "file_cs": "c:0-17215-2a28",
              "file_hash": "b2eae05f518a5b8dae97eeb4a5f1484f",
              "height": 1024,
              "uri": "v09044g40000ch19h8bc77udo8c6el8g",
              "url_key": "v09044g40000ch19h8bc77udo8c6el8g_h264_540p_1584593",
              "url_list": [
                "https://v19-us.tiktokcdn.com/ee396f2f014c7ce621889a2194cfb49e/644319ee/video/tos/useast2a/tos-useast2a-ve-0068c001/o8ydICVCAzh1novDRm9AtfWNxgkuQUhwIUIhyQ/?a=1233&ch=0&cr=3&dr=0&lr=all&cd=0%7C0%7C0%7C3&br=3094&bt=1547&cs=0&ds=6&ft=iueGFy7oZZv0PD1LBDqXg9w5J2vekEeC~&mime_type=video_mp4&qs=0&rc=NWVlZDY2ZDk4ZTc1O2RpOkBpam85O2c6Zjs8azMzNzczM0AyYjIzYjM0XmMxYTM1YmNgYSM1YmBscjRfZS5gLS1kMTZzcw%3D%3D&l=202304211718510101040280782CB0FEFA&btag=80000&cc=25",
                "https://v16m-us.tiktokcdn.com/8f05c20e17bd57ada5c13df1af599292/644319ee/video/tos/useast2a/tos-useast2a-ve-0068c001/o8ydICVCAzh1novDRm9AtfWNxgkuQUhwIUIhyQ/?a=1233&ch=0&cr=3&dr=0&lr=all&cd=0%7C0%7C0%7C3&br=3094&bt=1547&cs=0&ds=6&ft=iueGFy7oZZv0PD1LBDqXg9w5J2vekEeC~&mime_type=video_mp4&qs=0&rc=NWVlZDY2ZDk4ZTc1O2RpOkBpam85O2c6Zjs8azMzNzczM0AyYjIzYjM0XmMxYTM1YmNgYSM1YmBscjRfZS5gLS1kMTZzcw%3D%3D&l=202304211718510101040280782CB0FEFA&btag=80000&cc=24",
                "https://api16-normal-c-useast1a.tiktokv.com/aweme/v1/play/?video_id=v09044g40000ch19h8bc77udo8c6el8g&line=0&is_play_url=1&source=PackSourceEnum_PUBLISH&file_id=c7ffea8862d44bf5a67a63e36a5beb52"
              ],
              "width": 576
            },
            "quality_type": 20
          },
          {
            "HDR_bit": "",
            "HDR_type": "",
            "bit_rate": 703906,
            "dub_infos": null,
            "gear_name": "lower_540_0",
            "is_bytevc1": 0,
            "play_addr": {
              "data_size": 1742785,
              "file_cs": "c:0-17207-b68e",
              "file_hash": "b1642c067da2ce46f1d11d8c6ba587b5",
              "height": 1024,
              "uri": "v09044g40000ch19h8bc77udo8c6el8g",
              "url_key": "v09044g40000ch19h8bc77udo8c6el8g_h264_540p_703906",
              "url_list": [
                "https://v19-us.tiktokcdn.com/00a3ccd5288b9a143b72242257c36859/644319ee/video/tos/useast2a/tos-useast2a-ve-0068c002/ogJVCBChIkhtnxVRmoQU7EqIIAwyhNzswQWgfA/?a=1233&ch=0&cr=3&dr=0&lr=all&cd=0%7C0%7C0%7C3&br=1374&bt=687&cs=0&ds=6&ft=iueGFy7oZZv0PD1LBDqXg9w5J2vekEeC~&mime_type=video_mp4&qs=4&rc=OzxlNTk6Nzc5NTRpaDZoZEBpam85O2c6Zjs8azMzNzczM0AwYy4uYWMwX2ExLjEuNmNhYSM1YmBscjRfZS5gLS1kMTZzcw%3D%3D&l=202304211718510101040280782CB0FEFA&btag=80000&cc=25",
                "https://v16m-us.tiktokcdn.com/41e488cbee9f4d5b1907205d2c889688/644319ee/video/tos/useast2a/tos-useast2a-ve-0068c002/ogJVCBChIkhtnxVRmoQU7EqIIAwyhNzswQWgfA/?a=1233&ch=0&cr=3&dr=0&lr=all&cd=0%7C0%7C0%7C3&br=1374&bt=687&cs=0&ds=6&ft=iueGFy7oZZv0PD1LBDqXg9w5J2vekEeC~&mime_type=video_mp4&qs=4&rc=OzxlNTk6Nzc5NTRpaDZoZEBpam85O2c6Zjs8azMzNzczM0AwYy4uYWMwX2ExLjEuNmNhYSM1YmBscjRfZS5gLS1kMTZzcw%3D%3D&l=202304211718510101040280782CB0FEFA&btag=80000&cc=24",
                "https://api16-normal-c-useast1a.tiktokv.com/aweme/v1/play/?video_id=v09044g40000ch19h8bc77udo8c6el8g&line=0&is_play_url=1&source=PackSourceEnum_PUBLISH&file_id=dafe931e4f1142d6b434f7d6121bf938"
              ],
              "width": 576
            },
            "quality_type": 24
          },
          {
            "HDR_bit": "",
            "HDR_type": "",
            "bit_rate": 495084,
            "dub_infos": null,
            "gear_name": "lowest_540_0",
            "is_bytevc1": 0,
            "play_addr": {
              "data_size": 1225768,
              "file_cs": "c:0-17207-2312",
              "file_hash": "5f458d483e442a1f4c12c56ad9e1e6e3",
              "height": 1024,
              "uri": "v09044g40000ch19h8bc77udo8c6el8g",
              "url_key": "v09044g40000ch19h8bc77udo8c6el8g_h264_540p_495084",
              "url_list": [
                "https://v19-us.tiktokcdn.com/7cbcd6d38c653d1bb5e93b714c758ad9/644319ee/video/tos/useast2a/tos-useast2a-pve-0068/okQVhQRtIyhF1kgTAhzCnxfUKWjIoANIw9mBEC/?a=1233&ch=0&cr=3&dr=0&lr=all&cd=0%7C0%7C0%7C3&br=966&bt=483&cs=0&ds=6&ft=iueGFy7oZZv0PD1LBDqXg9w5J2vekEeC~&mime_type=video_mp4&qs=5&rc=aDpnaDRoaDU6OjtkOjdkaEBpam85O2c6Zjs8azMzNzczM0AwMTYuYzZjXi4xNl8xYzUtYSM1YmBscjRfZS5gLS1kMTZzcw%3D%3D&l=202304211718510101040280782CB0FEFA&btag=80000&cc=25",
                "https://v16m-us.tiktokcdn.com/00df0d296b9b10b2e4f28553a438512e/644319ee/video/tos/useast2a/tos-useast2a-pve-0068/okQVhQRtIyhF1kgTAhzCnxfUKWjIoANIw9mBEC/?a=1233&ch=0&cr=3&dr=0&lr=all&cd=0%7C0%7C0%7C3&br=966&bt=483&cs=0&ds=6&ft=iueGFy7oZZv0PD1LBDqXg9w5J2vekEeC~&mime_type=video_mp4&qs=5&rc=aDpnaDRoaDU6OjtkOjdkaEBpam85O2c6Zjs8azMzNzczM0AwMTYuYzZjXi4xNl8xYzUtYSM1YmBscjRfZS5gLS1kMTZzcw%3D%3D&l=202304211718510101040280782CB0FEFA&btag=80000&cc=24",
                "https://api16-normal-c-useast1a.tiktokv.com/aweme/v1/play/?video_id=v09044g40000ch19h8bc77udo8c6el8g&line=0&is_play_url=1&source=PackSourceEnum_PUBLISH&file_id=0e8af447ba984717a2fe9ef11e9d473e"
              ],
              "width": 576
            },
            "quality_type": 25
          }
        ],
        "cdn_url_expired": 0,
        "cover": {
          "height": 720,
          "uri": "tos-maliva-p-0068/ooQeFkdESBp7eQRG3GgAS8DBiMnxVQD7CbEhsJ",
          "url_list": [
            "https://p19-aimg-sign-va.tiktokcdn.com/tos-maliva-p-0068/ooQeFkdESBp7eQRG3GgAS8DBiMnxVQD7CbEhsJ~c5_300x400.webp?x-expires=1682182800&x-signature=CoAUfEmL%2FyWGCWqTfGiIfmOTcOw%3D&s=PUBLISH&se=false&sh=&sc=cover&l=202304211718510101040280782CB0FEFA",
            "https://p16-aimg-sign-va.tiktokcdn.com/tos-maliva-p-0068/ooQeFkdESBp7eQRG3GgAS8DBiMnxVQD7CbEhsJ~c5_300x400.webp?x-expires=1682182800&x-signature=caZbJvawPHSV7ykPcBWnyR3m94c%3D&s=PUBLISH&se=false&sh=&sc=cover&l=202304211718510101040280782CB0FEFA",
            "https://p19-aimg-sign-va.tiktokcdn.com/tos-maliva-p-0068/ooQeFkdESBp7eQRG3GgAS8DBiMnxVQD7CbEhsJ~c5_300x400.jpeg?x-expires=1682182800&x-signature=W2OVOQUhcHHrbZSa%2FhA9MY6Uy8E%3D&s=PUBLISH&se=false&sh=&sc=cover&l=202304211718510101040280782CB0FEFA"
          ],
          "width": 720
        },
        "download_addr": {
          "data_size": 1742785,
          "height": 720,
          "uri": "v09044g40000ch19h8bc77udo8c6el8g",
          "url_list": [
            "https://api16-normal-c-useast1a.tiktokv.com/aweme/v1/play/?video_id=v09044g40000ch19h8bc77udo8c6el8g&line=0&watermark=0&logo_name=tiktok_m&source=PUBLISH&file_id=dafe931e4f1142d6b434f7d6121bf938"
          ],
          "width": 720
        },
        "duration": 19807,
        "dynamic_cover": {
          "height": 720,
          "uri": "tos-maliva-p-0068/ecc90f0441a54c818f6fd0e11a04b143_1682086250",
          "url_list": [
            "https://p16-sign-va.tiktokcdn.com/obj/tos-maliva-p-0068/ecc90f0441a54c818f6fd0e11a04b143_1682086250?x-expires=1682182800&x-signature=MvYCh9a90FkwA2OjFc8E6BFel%2BY%3D&s=PUBLISH&se=false&sh=&sc=dynamic_cover&l=202304211718510101040280782CB0FEFA"
          ],
          "width": 720
        },
        "has_watermark": false,
        "height": 1024,
        "is_bytevc1": 0,
        "is_callback": true,
        "meta": "{\"LoudnessRange\":\"2.4\",\"LoudnessRangeEnd\":\"-10.4\",\"LoudnessRangeStart\":\"-12.8\",\"MaximumMomentaryLoudness\":\"-9\",\"MaximumShortTermLoudness\":\"-10.1\",\"Version\":\"1\",\"loudness\":\"-11.5\",\"peak\":\"0.98855\",\"qprf\":\"1.000\",\"sr_score\":\"1.000\"}",
        "need_set_token": false,
        "origin_cover": {
          "height": 720,
          "uri": "tos-maliva-p-0068/5b3ececfa77e4377b9fa71249b28a6df_1682086250",
          "url_list": [
            "https://p16-sign-va.tiktokcdn.com/tos-maliva-p-0068/5b3ececfa77e4377b9fa71249b28a6df_1682086250~tplv-tiktokx-360p.webp?x-expires=1682182800&x-signature=Swj2jyFNYezpHzeF4rbYf0xODjU%3D&s=PUBLISH&se=false&sh=&sc=feed_cover&l=202304211718510101040280782CB0FEFA",
            "https://p16-sign-va.tiktokcdn.com/tos-maliva-p-0068/5b3ececfa77e4377b9fa71249b28a6df_1682086250~tplv-tiktokx-360p.jpeg?x-expires=1682182800&x-signature=hgwH5nHWZsMCC%2FGvfTfTQ0JIiyQ%3D&s=PUBLISH&se=false&sh=&sc=feed_cover&l=202304211718510101040280782CB0FEFA"
          ],
          "width": 720
        },
        "play_addr": {
          "data_size": 3923255,
          "file_cs": "c:0-17215-2a28",
          "file_hash": "b2eae05f518a5b8dae97eeb4a5f1484f",
          "height": 1024,
          "uri": "v09044g40000ch19h8bc77udo8c6el8g",
          "url_key": "v09044g40000ch19h8bc77udo8c6el8g_h264_540p_1584593",
          "url_list": [
            "https://v19-us.tiktokcdn.com/ee396f2f014c7ce621889a2194cfb49e/644319ee/video/tos/useast2a/tos-useast2a-ve-0068c001/o8ydICVCAzh1novDRm9AtfWNxgkuQUhwIUIhyQ/?a=1233&ch=0&cr=3&dr=0&lr=all&cd=0%7C0%7C0%7C3&br=3094&bt=1547&cs=0&ds=6&ft=iueGFy7oZZv0PD1LBDqXg9w5J2vekEeC~&mime_type=video_mp4&qs=0&rc=NWVlZDY2ZDk4ZTc1O2RpOkBpam85O2c6Zjs8azMzNzczM0AyYjIzYjM0XmMxYTM1YmNgYSM1YmBscjRfZS5gLS1kMTZzcw%3D%3D&l=202304211718510101040280782CB0FEFA&btag=80000&cc=25",
            "https://v16m-us.tiktokcdn.com/8f05c20e17bd57ada5c13df1af599292/644319ee/video/tos/useast2a/tos-useast2a-ve-0068c001/o8ydICVCAzh1novDRm9AtfWNxgkuQUhwIUIhyQ/?a=1233&ch=0&cr=3&dr=0&lr=all&cd=0%7C0%7C0%7C3&br=3094&bt=1547&cs=0&ds=6&ft=iueGFy7oZZv0PD1LBDqXg9w5J2vekEeC~&mime_type=video_mp4&qs=0&rc=NWVlZDY2ZDk4ZTc1O2RpOkBpam85O2c6Zjs8azMzNzczM0AyYjIzYjM0XmMxYTM1YmNgYSM1YmBscjRfZS5gLS1kMTZzcw%3D%3D&l=202304211718510101040280782CB0FEFA&btag=80000&cc=24",
            "https://api16-normal-c-useast1a.tiktokv.com/aweme/v1/play/?video_id=v09044g40000ch19h8bc77udo8c6el8g&line=0&is_play_url=1&source=PackSourceEnum_PUBLISH&file_id=c7ffea8862d44bf5a67a63e36a5beb52"
          ],
          "width": 576
        },
        "ratio": "540p",
        "source_HDR_type": 0,
        "tags": null,
        "width": 576
      },
      "video_control": {
        "allow_download": false,
        "allow_duet": true,
        "allow_dynamic_wallpaper": true,
        "allow_music": true,
        "allow_react": true,
        "allow_stitch": true,
        "draft_progress_bar": 0,
        "prevent_download_type": 2,
        "share_type": 0,
        "show_progress_bar": 0,
        "timer_status": 1
      },
      "video_labels": [],
      "video_text": [],
      "voice_filter_ids": null,
      "with_promotional_music": false,
      "without_watermark": false
    }
  ],
  "extra": {
    "fatal_item_ids": [],
    "logid": "202304211718510101040280782CB0FEFA",
    "now": 1682097531000
  },
  "has_locate_item": false,
  "has_more": 0,
  "log_pb": {
    "impr_id": "202304211718510101040280782CB0FEFA"
  },
  "max_cursor": 1682086248000,
  "min_cursor": 1682086248000,
  "status_code": 0
}